pychurn/__init__.py
pychurn/cli.py
pychurn/complexity.py
pychurn/parse.py
pychurn/repo.py
pychurn/utils.py
pychurn/gitsource/__init__.py
pychurn/gitsource/gitsource.py
pychurn/gitsource/libgitsource.py
pychurn/gitsource/pygitsource.py
pychurn-0.2.0.dist-info/DESCRIPTION.rst
pychurn-0.2.0.dist-info/METADATA
pychurn-0.2.0.dist-info/RECORD
pychurn-0.2.0.dist-info/WHEEL
pychurn-0.2.0.dist-info/entry_points.txt
pychurn-0.2.0.dist-info/metadata.json
pychurn-0.2.0.dist-info/top_level.txt
