Metadata-Version: 2.0
Name: pychurn
Version: 0.2.0
Summary: Identifying hotspots in python code
Home-page: https://github.com/jmcarp/pychurn
Author: Joshua Carp
Author-email: jm.carp@gmail.com
License: Copyright 2016 Joshua Carp
Requires-Dist: GitPython
Requires-Dist: click
Requires-Dist: python-dateutil
Requires-Dist: radon
Requires-Dist: six
Requires-Dist: tabulate
